[{"Symbol":"GS","Name":"The Goldman Sachs Group, Inc.","Weight":"11.66%","Chg":"11.95","% Chg":"(1.27%)"},{"Symbol":"CAT","Name":"Caterpillar Inc.","Weight":"9.10%","Chg":"3.32","% Chg":"(0.45%)"},{"Symbol":"MSFT","Name":"Microsoft Corporation","Weight":"5.13%","Chg":"6.91","% Chg":"(1.67%)"},{"Symbol":"HD","Name":"The Home Depot, Inc.","Weight":"4.76%","Chg":"8.86","% Chg":"(2.32%)"},{"Symbol":"AMGN","Name":"Amgen Inc.","Weight":"4.50%","Chg":"-7.28","% Chg":"(-1.94%)"},{"Symbol":"AXP","Name":"American Express Company","Weight":"4.46%","Chg":"6.01","% Chg":"(1.67%)"},{"Symbol":"SHW","Name":"Sherwin-Williams","Weight":"4.45%","Chg":"4.33","% Chg":"(1.20%)"},{"Symbol":"V","Name":"Visa Inc.","Weight":"4.01%","Chg":"3.24","% Chg":"(0.99%)"},{"Symbol":"MCD","Name":"McDonald's Corporation","Weight":"3.98%","Chg":"0.1","% Chg":"(0.03%)"},{"Symbol":"JPM","Name":"JPMorgan Chase & Co.","Weight":"3.94%","Chg":"0.4","% Chg":"(0.12%)"},{"Symbol":"TRV","Name":"The Travelers Companies, Inc.","Weight":"3.61%","Chg":"3.32","% Chg":"(1.13%)"},{"Symbol":"IBM","Name":"International Business Machines Corporation","Weight":"3.59%","Chg":"-2.62","% Chg":"(-0.88%)"},{"Symbol":"UNH","Name":"UnitedHealth Group Incorporated","Weight":"3.38%","Chg":"0.87","% Chg":"(0.31%)"},{"Symbol":"AAPL","Name":"Apple Inc.","Weight":"3.34%","Chg":"-1.37","% Chg":"(-0.50%)"},{"Symbol":"BA","Name":"The Boeing Company","Weight":"2.98%","Chg":"-0.63","% Chg":"(-0.26%)"},{"Symbol":"HON","Name":"Honeywell International Inc.","Weight":"2.98%","Chg":"4.07","% Chg":"(1.70%)"},{"Symbol":"JNJ","Name":"Johnson & Johnson","Weight":"2.91%","Chg":"-0.08","% Chg":"(-0.04%)"},{"Symbol":"AMZN","Name":"Amazon.com, Inc.amazon.com","Weight":"2.56%","Chg":"1.37","% Chg":"(0.66%)"},{"Symbol":"CRM","Name":"Salesforce, Inc.","Weight":"2.39%","Chg":"1.64","% Chg":"(0.85%)"},{"Symbol":"NVDA","Name":"Nvidia","Weight":"2.32%","Chg":"-0.08","% Chg":"(-0.04%)"},{"Symbol":"CVX","Name":"Chevron Corporation","Weight":"2.22%","Chg":"-0.64","% Chg":"(-0.35%)"},{"Symbol":"MMM","Name":"3M Company","Weight":"2.11%","Chg":"2.66","% Chg":"(1.56%)"},{"Symbol":"PG","Name":"The Procter & Gamble Company","Weight":"1.93%","Chg":"1.13","% Chg":"(0.72%)"},{"Symbol":"WMT","Name":"Walmart Inc.","Weight":"1.55%","Chg":"-1.98","% Chg":"(-1.53%)"},{"Symbol":"MRK","Name":"Merck & Co., Inc.","Weight":"1.43%","Chg":"-0.78","% Chg":"(-0.66%)"},{"Symbol":"DIS","Name":"The Walt Disney Company","Weight":"1.35%","Chg":"3.09","% Chg":"(2.89%)"},{"Symbol":"CSCO","Name":"Cisco Systems, Inc.","Weight":"1.07%","Chg":"0.75","% Chg":"(0.86%)"},{"Symbol":"KO","Name":"The Coca-Cola Company","Weight":"0.93%","Chg":"-1.57","% Chg":"(-2.02%)"},{"Symbol":"NKE","Name":"Nike, Inc.","Weight":"0.78%","Chg":"1.29","% Chg":"(2.06%)"},{"Symbol":"VZ","Name":"Verizon Communications Inc.","Weight":"0.58%","Chg":"0.58","% Chg":"(1.24%)"}]