[{"Symbol":"GS","Name":"The Goldman Sachs Group, Inc.","Weight":"11.46%","Chg":"-13.72","% Chg":"(-1.47%)"},{"Symbol":"CAT","Name":"Caterpillar Inc.","Weight":"9.45%","Chg":"7.08","% Chg":"(0.94%)"},{"Symbol":"MSFT","Name":"Microsoft Corporation","Weight":"4.98%","Chg":"0.07","% Chg":"(0.02%)"},{"Symbol":"HD","Name":"The Home Depot, Inc.","Weight":"4.72%","Chg":"-4.46","% Chg":"(-1.16%)"},{"Symbol":"AMGN","Name":"Amgen Inc.","Weight":"4.70%","Chg":"-2.75","% Chg":"(-0.72%)"},{"Symbol":"SHW","Name":"Sherwin-Williams","Weight":"4.49%","Chg":"-5.38","% Chg":"(-1.47%)"},{"Symbol":"AXP","Name":"American Express Company","Weight":"4.24%","Chg":"-5.86","% Chg":"(-1.69%)"},{"Symbol":"MCD","Name":"McDonald's Corporation","Weight":"4.11%","Chg":"2.46","% Chg":"(0.75%)"},{"Symbol":"V","Name":"Visa Inc.","Weight":"3.94%","Chg":"-3.9","% Chg":"(-1.22%)"},{"Symbol":"JPM","Name":"JPMorgan Chase & Co.","Weight":"3.83%","Chg":"-1.23","% Chg":"(-0.40%)"},{"Symbol":"TRV","Name":"The Travelers Companies, Inc.","Weight":"3.71%","Chg":"-0.75","% Chg":"(-0.25%)"},{"Symbol":"UNH","Name":"UnitedHealth Group Incorporated","Weight":"3.58%","Chg":"-0.44","% Chg":"(-0.15%)"},{"Symbol":"AAPL","Name":"Apple Inc.","Weight":"3.29%","Chg":"-0.54","% Chg":"(-0.21%)"},{"Symbol":"IBM","Name":"International Business Machines Corporation","Weight":"3.20%","Chg":"-3.81","% Chg":"(-1.46%)"},{"Symbol":"JNJ","Name":"Johnson & Johnson","Weight":"3.06%","Chg":"0.36","% Chg":"(0.15%)"},{"Symbol":"HON","Name":"Honeywell International Inc.","Weight":"3.00%","Chg":"-0.24","% Chg":"(-0.10%)"},{"Symbol":"BA","Name":"The Boeing Company","Weight":"2.95%","Chg":"-2.33","% Chg":"(-0.97%)"},{"Symbol":"AMZN","Name":"Amazon.com, Inc.amazon.com","Weight":"2.55%","Chg":"0.32","% Chg":"(0.15%)"},{"Symbol":"NVDA","Name":"Nvidia","Weight":"2.34%","Chg":"-0.44","% Chg":"(-0.23%)"},{"Symbol":"CVX","Name":"Chevron Corporation","Weight":"2.32%","Chg":"2.41","% Chg":"(1.31%)"},{"Symbol":"CRM","Name":"Salesforce, Inc.","Weight":"2.30%","Chg":"-3.06","% Chg":"(-1.63%)"},{"Symbol":"MMM","Name":"3M Company","Weight":"2.05%","Chg":"0.13","% Chg":"(0.08%)"},{"Symbol":"PG","Name":"The Procter & Gamble Company","Weight":"1.97%","Chg":"1.53","% Chg":"(0.97%)"},{"Symbol":"WMT","Name":"Walmart Inc.","Weight":"1.58%","Chg":"0.16","% Chg":"(0.13%)"},{"Symbol":"MRK","Name":"Merck & Co., Inc.","Weight":"1.51%","Chg":"-0.72","% Chg":"(-0.59%)"},{"Symbol":"DIS","Name":"The Walt Disney Company","Weight":"1.32%","Chg":"-1.28","% Chg":"(-1.20%)"},{"Symbol":"KO","Name":"The Coca-Cola Company","Weight":"0.98%","Chg":"-0.7","% Chg":"(-0.89%)"},{"Symbol":"CSCO","Name":"Cisco Systems, Inc.","Weight":"0.97%","Chg":"0.07","% Chg":"(0.09%)"},{"Symbol":"NKE","Name":"Nike, Inc.","Weight":"0.80%","Chg":"-1.14","% Chg":"(-1.74%)"},{"Symbol":"VZ","Name":"Verizon Communications Inc.","Weight":"0.61%","Chg":"0.67","% Chg":"(1.40%)"}]